{"version":{"fullVersion":"1.4.33","major":"1","minor":"4","patch":"33"},"meta":{"flags":["experimentalData"]},"collections":[{"label":"Page Content","name":"page","path":"public/content/page","format":"mdx","fields":[{"name":"body","label":"Main Content","type":"rich-text","isBody":true,"namespace":["page","body"],"searchable":true,"parser":{"type":"mdx"},"uid":false},{"name":"sections","label":"Sections","type":"object","list":true,"ui":{},"fields":[{"name":"title","label":"Title","type":"string","namespace":["page","sections","title"],"searchable":true,"uid":false},{"name":"body","label":"Body","type":"rich-text","namespace":["page","sections","body"],"searchable":true,"parser":{"type":"mdx"},"uid":false}],"namespace":["page","sections"],"searchable":true,"uid":false}],"ui":{},"namespace":["page"]},{"label":"Blog Posts","name":"post","path":"public/content/post","fields":[{"type":"string","label":"Title","name":"title","namespace":["post","title"],"searchable":true,"uid":false},{"type":"string","label":"Blog Post Body","name":"body","isBody":true,"ui":{"component":"textarea"},"namespace":["post","body"],"searchable":true,"uid":false}],"ui":{},"namespace":["post"]},{"label":"Navigation","name":"nav","path":"public/content/nav","format":"mdx","create":true,"fields":[{"name":"title","label":"Title","type":"string","namespace":["nav","title"],"searchable":true,"uid":false},{"name":"links","label":"Links","type":"object","list":true,"ui":{},"fields":[{"name":"title","label":"Title","type":"string","namespace":["nav","links","title"],"searchable":true,"uid":false},{"name":"path","label":"path","type":"string","namespace":["nav","links","path"],"searchable":true,"uid":false},{"name":"sublinks","label":"Sublinks","type":"object","list":true,"ui":{},"fields":[{"name":"title","label":"Title","type":"string","namespace":["nav","links","sublinks","title"],"searchable":true,"uid":false},{"name":"path","label":"path","type":"string","namespace":["nav","links","sublinks","path"],"searchable":true,"uid":false}],"namespace":["nav","links","sublinks"],"searchable":true,"uid":false}],"namespace":["nav","links"],"searchable":true,"uid":false}],"ui":{},"namespace":["nav"]}],"config":{"media":{"tina":{"publicFolder":"public","mediaRoot":"uploads"}}}}